oplusclient/__init__.py
oplusclient/client.py
oplusclient/exceptions.py
oplusclient/rest_client.py
oplusclient/task.py
oplusclient/util.py
oplusclient/version.py
oplusclient/endpoints/__init__.py
oplusclient/endpoints/base.py
oplusclient/endpoints/simulation.py
oplusclient/models/__init__.py
oplusclient/models/base.py
oplusclient/models/floorspace.py
oplusclient/models/generic_simulation_group.py
oplusclient/models/geometry.py
oplusclient/models/import_export_base.py
oplusclient/models/mono_simulation_group.py
oplusclient/models/multi_simulation_group.py
oplusclient/models/obat.py
oplusclient/models/organization.py
oplusclient/models/project.py
oplusclient/models/simulation.py
oplusclient/models/simulation_group.py
oplusclient/models/weather.py
oplusclient/tools/__init__.py
oplusclient/tools/floorspace.py
oplusclient/tools/resources/empty_floorplan.flo
tests/__init__.py
tests/test_pass.py
to_relink/__init__.py
to_relink/base.py
to_relink/test_generic_simulation_group.py
to_relink/test_geometry.py
to_relink/test_multi_simulation_group.py
to_relink/test_obat.py
to_relink/test_pass.py
to_relink/test_simulation.py
to_relink/test_weather.py
oplusclient-1.8.3.dist-info/LICENSE.txt
oplusclient-1.8.3.dist-info/METADATA
oplusclient-1.8.3.dist-info/WHEEL
oplusclient-1.8.3.dist-info/top_level.txt
oplusclient-1.8.3.dist-info/RECORD
